{
  "expense": [
    {
      "id": "food",
      "name": "Еда",
      "subcategories": [
        "Супермаркет",
        "Кафе и рестораны",
        "Доставка еды",
        "Алкоголь",
        "Обеды на работе",
        "Фастфуд",
        "Продукты питания"
      ]
    },
    {
      "id": "transport",
      "name": "Транспорт",
      "subcategories": [
        "Общественный транспорт",
        "Такси",
        "Каршеринг",
        "Бензин",
        "Парковка",
        "Ремонт автомобиля",
        "Страховка автомобиля",
        "Штрафы ГИБДД"
      ]
    },
    {
      "id": "housing",
      "name": "Жильё",
      "subcategories": [
        "Аренда",
        "Коммунальные услуги",
        "Интернет",
        "Телефон",
        "Телевидение",
        "Мебель",
        "Бытовая техника",
        "Ремонт",
        "Хозяйственные товары",
        "Уборка"
      ]
    },
    {
      "id": "entertainment",
      "name": "Развлечения",
      "subcategories": [
        "Кино",
        "Концерты",
        "Театры",
        "Игры",
        "Хобби",
        "Книги",
        "Музеи",
        "Парки развлечений",
        "Путешествия",
        "Отели"
      ]
    },
    {
      "id": "health",
      "name": "Здоровье",
      "subcategories": [
        "Аптека",
        "Врачи",
        "Стоматолог",
        "Анализы",
        "Спорт",
        "Фитнес",
        "Страховка",
        "Витамины",
        "Медицинское оборудование"
      ]
    },
    {
      "id": "clothing",
      "name": "Одежда",
      "subcategories": [
        "Одежда",
        "Обувь",
        "Аксессуары",
        "Химчистка",
        "Ремонт одежды",
        "Нижнее бельё"
      ]
    },
    {
      "id": "personal",
      "name": "Личные расходы",
      "subcategories": [
        "Косметика",
        "Парикмахерская",
        "Салоны красоты",
        "Гигиена",
        "Парфюмерия",
        "Маникюр и педикюр"
      ]
    },
    {
      "id": "gifts",
      "name": "Подарки и благотворительность",
      "subcategories": [
        "Подарки",
        "Благотворительность",
        "Цветы",
        "Праздники"
      ]
    },
    {
      "id": "finance",
      "name": "Финансы",
      "subcategories": [
        "Комиссии банка",
        "Страховки",
        "Инвестиции",
        "Кредиты",
        "Налоги",
        "Штрафы",
        "Проценты по кредитам"
      ]
    },
    {
      "id": "subscriptions",
      "name": "Подписки",
      "subcategories": [
        "Стриминговые сервисы",
        "Подписки на софт",
        "Подписки на сервисы",
        "Газеты и журналы",
        "Облачные сервисы"
      ]
    },
    {
      "id": "education",
      "name": "Образование",
      "subcategories": [
        "Курсы",
        "Обучение",
        "Книги и учебники",
        "Канцтовары",
        "Репетиторы",
        "Семинары и конференции"
      ]
    },
    {
      "id": "children",
      "name": "Дети",
      "subcategories": [
        "Детская одежда",
        "Игрушки",
        "Образование детей",
        "Детское питание",
        "Детские развлечения",
        "Кружки и секции"
      ]
    },
    {
      "id": "pets",
      "name": "Домашние животные",
      "subcategories": [
        "Корм для животных",
        "Ветеринар",
        "Аксессуары для животных",
        "Груминг",
        "Страховка для животных"
      ]
    },
    {
      "id": "shopping",
      "name": "Покупки",
      "subcategories": [
        "Электроника",
        "Техника",
        "Инструменты",
        "Спортивные товары",
        "Товары для дома",
        "Подарочные карты"
      ]
    },
    {
      "id": "services",
      "name": "Услуги",
      "subcategories": [
        "Юридические услуги",
        "Бухгалтерские услуги",
        "Ремонтные услуги",
        "Клининговые услуги",
        "Доставка",
        "Прочие услуги"
      ]
    },
    {
      "id": "other",
      "name": "Прочее",
      "subcategories": [
        "Непредвиденные расходы",
        "Другое"
      ]
    }
  ],
  "income": [
    {
      "id": "salary",
      "name": "Зарплата",
      "subcategories": null
    },
    {
      "id": "bonus",
      "name": "Премия",
      "subcategories": null
    },
    {
      "id": "freelance",
      "name": "Фриланс",
      "subcategories": null
    },
    {
      "id": "business",
      "name": "Бизнес",
      "subcategories": null
    },
    {
      "id": "investment",
      "name": "Инвестиции",
      "subcategories": null
    },
    {
      "id": "rental",
      "name": "Аренда",
      "subcategories": null
    },
    {
      "id": "gift",
      "name": "Подарок",
      "subcategories": null
    },
    {
      "id": "refund",
      "name": "Возврат",
      "subcategories": null
    },
    {
      "id": "cashback",
      "name": "Кешбэк",
      "subcategories": null
    },
    {
      "id": "other_income",
      "name": "Прочее",
      "subcategories": null
    }
  ]
}